{"nodes": [{"id": "c_users_ashu_documents_wakewordprod_core_common_tensor_h", "label": "tensor.h", "file_type": "code", "source_file": "C:\\Users\\Ashu\\Documents\\wakewordprod\\core\\common\\tensor.h", "source_location": "L1"}, {"id": "tensor_arena", "label": "Arena()", "file_type": "code", "source_file": "C:\\Users\\Ashu\\Documents\\wakewordprod\\core\\common\\tensor.h", "source_location": "L42"}, {"id": "tensor_backendkind", "label": "BackendKind()", "file_type": "code", "source_file": "C:\\Users\\Ashu\\Documents\\wakewordprod\\core\\common\\tensor.h", "source_location": "L100"}], "edges": [{"source": "c_users_ashu_documents_wakewordprod_core_common_tensor_h", "target": "array", "relation": "imports", "confidence": "EXTRACTED", "source_file": "C:\\Users\\Ashu\\Documents\\wakewordprod\\core\\common\\tensor.h", "source_location": "L16", "weight": 1.0}, {"source": "c_users_ashu_documents_wakewordprod_core_common_tensor_h", "target": "cstddef", "relation": "imports", "confidence": "EXTRACTED", "source_file": "C:\\Users\\Ashu\\Documents\\wakewordprod\\core\\common\\tensor.h", "source_location": "L17", "weight": 1.0}, {"source": "c_users_ashu_documents_wakewordprod_core_common_tensor_h", "target": "cstdint", "relation": "imports", "confidence": "EXTRACTED", "source_file": "C:\\Users\\Ashu\\Documents\\wakewordprod\\core\\common\\tensor.h", "source_location": "L18", "weight": 1.0}, {"source": "c_users_ashu_documents_wakewordprod_core_common_tensor_h", "target": "aligned_alloc", "relation": "imports", "confidence": "EXTRACTED", "source_file": "C:\\Users\\Ashu\\Documents\\wakewordprod\\core\\common\\tensor.h", "source_location": "L20", "weight": 1.0}, {"source": "c_users_ashu_documents_wakewordprod_core_common_tensor_h", "target": "tensor_arena", "relation": "contains", "confidence": "EXTRACTED", "source_file": "C:\\Users\\Ashu\\Documents\\wakewordprod\\core\\common\\tensor.h", "source_location": "L42", "weight": 1.0}, {"source": "c_users_ashu_documents_wakewordprod_core_common_tensor_h", "target": "tensor_backendkind", "relation": "contains", "confidence": "EXTRACTED", "source_file": "C:\\Users\\Ashu\\Documents\\wakewordprod\\core\\common\\tensor.h", "source_location": "L100", "weight": 1.0}], "raw_calls": [{"caller_nid": "tensor_arena", "callee": "AlignedFree", "source_file": "C:\\Users\\Ashu\\Documents\\wakewordprod\\core\\common\\tensor.h", "source_location": "L46"}]}